README.txt
astrid.py
setup.py
python_astrid.egg-info/PKG-INFO
python_astrid.egg-info/SOURCES.txt
python_astrid.egg-info/dependency_links.txt
python_astrid.egg-info/top_level.txt