Metadata-Version: 1.1
Name: python-astrid
Version: 0.1
Summary: Python Distribution Utilities
Home-page: https://bitbucket.org/dusty/python-astrid/
Author: Dusty Phillips
Author-email: dusty@buchuki.com
License: UNKNOWN
Platform: UNKNOWN
Requires: requests
